pyqt_moving_label/__init__.py
pyqt_moving_label/movingLabel.py
pyqt_moving_label-0.0.2.dist-info/LICENSE
pyqt_moving_label-0.0.2.dist-info/METADATA
pyqt_moving_label-0.0.2.dist-info/WHEEL
pyqt_moving_label-0.0.2.dist-info/top_level.txt
pyqt_moving_label-0.0.2.dist-info/RECORD
