Metadata-Version: 2.1
Name: pyqt-moving-label
Version: 0.0.2
Summary: PyQt label which is moving from left to right
Home-page: https://github.com/yjg30737/pyqt-moving-label.git
Author: Jung Gyu Yoon
Author-email: yjg30737@gmail.com
License: MIT
Platform: UNKNOWN
License-File: LICENSE
Requires-Dist: PyQt5 (>=5.8)
